pip_test_zzq/__init__.py
pip_test_zzq/func.py
pip_test_zzq-1.0.dist-info/LICENSE
pip_test_zzq-1.0.dist-info/METADATA
pip_test_zzq-1.0.dist-info/WHEEL
pip_test_zzq-1.0.dist-info/top_level.txt
pip_test_zzq-1.0.dist-info/RECORD
